{
  "neo1-1st-18": {
    "cardId": "neo1-1st-18",
    "consensusPriceCents": 535000,
    "confidenceLower": 337500,
    "confidenceUpper": 535000,
    "contributingSources": [
      {
        "platform": "pricecharting",
        "family": "ebay-sold",
        "kind": "realized",
        "priceCents": 535000,
        "confidence": 0.8,
        "reliability": 0.8972183673171252,
        "weight": 0.6215399143478915,
        "source": "pc_sold",
        "compCount": 3
      },
      {
        "platform": "psa-apr",
        "family": "psa-apr",
        "kind": "realized",
        "priceCents": 337500,
        "confidence": 0.85,
        "reliability": 0.22984348155112216,
        "weight": 0.3383466026695901,
        "source": "psa-apr",
        "compCount": 3
      },
      {
        "platform": "point130",
        "family": "ebay-sold",
        "kind": "realized",
        "priceCents": 362500,
        "confidence": 0.5,
        "reliability": 5.314409999999999e-7,
        "weight": 1.878711715859569e-7,
        "source": "point130-sold",
        "compCount": 2
      },
      {
        "platform": "ebay",
        "family": "ebay-sold",
        "kind": "ask",
        "priceCents": 600000,
        "confidence": 0.5,
        "reliability": 0.7381476569001224,
        "weight": 0,
        "source": "ebay_active",
        "compCount": 4
      },
      {
        "platform": "alt",
        "family": "alt",
        "kind": "ask",
        "priceCents": 650000,
        "confidence": 0.4,
        "reliability": 0.3313823183244855,
        "weight": 0,
        "source": "alt-ask",
        "compCount": 1
      }
    ],
    "rejectedSources": [
      {
        "platform": "fanatics",
        "priceCents": 2500000,
        "reason": "MAD outlier (z=14.01)",
        "zScore": 14.010816455696203
      }
    ],
    "flags": [
      "insufficient_sources"
    ],
    "sourceCount": 2,
    "roundId": "neo1-1st-18_1781082046312",
    "timestamp": "2026-06-10T09:00:46.312Z",
    "rawSourceCount": 3,
    "sourceFamilies": [
      "ebay-sold",
      "psa-apr"
    ],
    "askCount": 2,
    "lowestAskCents": 600000
  },
  "jp-vs-091": {
    "cardId": "jp-vs-091",
    "consensusPriceCents": 1588230,
    "confidenceLower": 1588230,
    "confidenceUpper": 1588230,
    "contributingSources": [
      {
        "platform": "pricecharting",
        "family": "ebay-sold",
        "kind": "realized",
        "priceCents": 1588230,
        "confidence": 0.9,
        "reliability": 0.898378993341205,
        "weight": 1.8077458608119976,
        "source": "pc_sold",
        "compCount": 5
      },
      {
        "platform": "ebay",
        "family": "ebay-sold",
        "kind": "ask",
        "priceCents": 1850000,
        "confidence": 0.6,
        "reliability": 0.7395545332905091,
        "weight": 0,
        "source": "ebay_active",
        "compCount": 5
      },
      {
        "platform": "cardmarket",
        "family": "cardmarket",
        "kind": "ask",
        "priceCents": 1674000,
        "confidence": 0.5,
        "reliability": 0.6019539098310336,
        "weight": 0,
        "source": "cardmarket-eu-ask",
        "compCount": 2
      }
    ],
    "rejectedSources": [
      {
        "platform": "fanatics",
        "priceCents": 2700000,
        "reason": "implausible vs anchor (1.70x of $15882, thin source)"
      }
    ],
    "flags": [
      "insufficient_sources"
    ],
    "sourceCount": 1,
    "roundId": "jp-vs-091_1781082046312",
    "timestamp": "2026-06-10T09:00:46.312Z",
    "rawSourceCount": 1,
    "sourceFamilies": [
      "ebay-sold"
    ],
    "askCount": 2,
    "lowestAskCents": 1674000
  },
  "base5-1st-83": {
    "cardId": "base5-1st-83",
    "consensusPriceCents": 798656,
    "confidenceLower": 793000,
    "confidenceUpper": 798656,
    "contributingSources": [
      {
        "platform": "goldin",
        "family": "goldin",
        "kind": "realized",
        "priceCents": 793000,
        "confidence": 0.8,
        "reliability": 0.39460085489988167,
        "weight": 0.3156469280392303,
        "source": "goldin-auctions",
        "compCount": 1
      },
      {
        "platform": "pricecharting",
        "family": "ebay-sold",
        "kind": "realized",
        "priceCents": 798656,
        "confidence": 0.9,
        "reliability": 0.8995136980023615,
        "weight": 0.9050145981698078,
        "source": "pc_sold",
        "compCount": 5
      },
      {
        "platform": "fanatics",
        "family": "fanatics-pwcc",
        "kind": "realized",
        "priceCents": 470000,
        "confidence": 0.7,
        "reliability": 0.17671954582563165,
        "weight": 0.12368946310785231,
        "source": "fanatics-pwcc",
        "compCount": 1
      },
      {
        "platform": "point130",
        "family": "ebay-sold",
        "kind": "realized",
        "priceCents": 589000,
        "confidence": 0.72,
        "reliability": 1.5943229999999994e-7,
        "weight": 9.940252228986703e-8,
        "source": "point130-sold",
        "compCount": 3
      },
      {
        "platform": "ebay",
        "family": "ebay-sold",
        "kind": "ask",
        "priceCents": 1499995,
        "confidence": 0.125,
        "reliability": 0.7359288599871527,
        "weight": 0,
        "source": "ebay_active",
        "compCount": 1
      },
      {
        "platform": "alt",
        "family": "alt",
        "kind": "ask",
        "priceCents": 527250,
        "confidence": 0.4,
        "reliability": 0.3279861240687742,
        "weight": 0,
        "source": "alt-ask",
        "compCount": 1
      }
    ],
    "rejectedSources": [
      {
        "platform": "psa-apr",
        "priceCents": 397000,
        "reason": "implausible vs anchor (0.50x of $7987)"
      }
    ],
    "flags": [
      "consensus_above_lowest_ask"
    ],
    "sourceCount": 3,
    "roundId": "base5-1st-83_1781082046312",
    "timestamp": "2026-06-10T09:00:46.312Z",
    "rawSourceCount": 4,
    "sourceFamilies": [
      "goldin",
      "ebay-sold",
      "fanatics-pwcc"
    ],
    "askCount": 2,
    "lowestAskCents": 527250
  },
  "base2-1st-3": {
    "cardId": "base2-1st-3",
    "consensusPriceCents": 730000,
    "confidenceLower": 730000,
    "confidenceUpper": 730000,
    "contributingSources": [
      {
        "platform": "pricecharting",
        "family": "ebay-sold",
        "kind": "realized",
        "priceCents": 730000,
        "confidence": 0.8500000000000001,
        "reliability": 0.9006233401699392,
        "weight": 1.5308844721032207,
        "source": "pc_sold",
        "compCount": 4
      },
      {
        "platform": "ebay",
        "family": "ebay-sold",
        "kind": "ask",
        "priceCents": 795000,
        "confidence": 0.6,
        "reliability": 0.7308561773759907,
        "weight": 0,
        "source": "ebay_active",
        "compCount": 6
      }
    ],
    "rejectedSources": [
      {
        "platform": "goldin",
        "priceCents": 40500,
        "reason": "implausible vs anchor (0.06x of $7300, thin source)"
      },
      {
        "platform": "fanatics",
        "priceCents": 338000,
        "reason": "implausible vs anchor (0.46x of $7300, thin source)"
      },
      {
        "platform": "psa-apr",
        "priceCents": 300100,
        "reason": "implausible vs anchor (0.41x of $7300)"
      },
      {
        "platform": "alt",
        "priceCents": 252000,
        "reason": "listing off-anchor (0.35x of $7300 — likely wrong grade/variant)"
      }
    ],
    "flags": [
      "insufficient_sources"
    ],
    "sourceCount": 1,
    "roundId": "base2-1st-3_1781082046313",
    "timestamp": "2026-06-10T09:00:46.313Z",
    "rawSourceCount": 1,
    "sourceFamilies": [
      "ebay-sold"
    ],
    "askCount": 1,
    "lowestAskCents": 795000
  }
}