{
  "neo1-1st-18": {
    "cardId": "neo1-1st-18",
    "consensusPriceCents": 535000,
    "confidenceLower": 337500,
    "confidenceUpper": 535000,
    "contributingSources": [
      {
        "platform": "pricecharting",
        "family": "ebay-sold",
        "kind": "realized",
        "priceCents": 535000,
        "confidence": 0.8,
        "reliability": 0.8742363717062611,
        "weight": 0.5903412004466768,
        "source": "pc_sold",
        "compCount": 3
      },
      {
        "platform": "psa-apr",
        "family": "psa-apr",
        "kind": "realized",
        "priceCents": 337500,
        "confidence": 0.85,
        "reliability": 0.29175480117351626,
        "weight": 0.4294937348770637,
        "source": "psa-apr",
        "compCount": 3
      },
      {
        "platform": "point130",
        "family": "ebay-sold",
        "kind": "realized",
        "priceCents": 362500,
        "confidence": 0.5,
        "reliability": 0.0081,
        "weight": 0.0028635139304990787,
        "source": "point130-sold",
        "compCount": 2
      },
      {
        "platform": "ebay",
        "family": "ebay-sold",
        "kind": "ask",
        "priceCents": 600000,
        "confidence": 0.5,
        "reliability": 0.7729260007563385,
        "weight": 0,
        "source": "ebay_active",
        "compCount": 4
      },
      {
        "platform": "courtyard",
        "family": "courtyard",
        "kind": "ask",
        "priceCents": 351046,
        "confidence": 0.95,
        "reliability": 0.8231539724917363,
        "weight": 0,
        "source": "courtyard_seeded",
        "compCount": 10
      },
      {
        "platform": "tcgplayer",
        "family": "tcgplayer",
        "kind": "ask",
        "priceCents": 356644,
        "confidence": 0.95,
        "reliability": 0.7340022741596267,
        "weight": 0,
        "source": "tcgplayer_seeded",
        "compCount": 12
      },
      {
        "platform": "alt",
        "family": "alt",
        "kind": "ask",
        "priceCents": 531360,
        "confidence": 0.3333333333333333,
        "reliability": 0.3342198809116223,
        "weight": 0,
        "source": "alt_sold",
        "compCount": 1
      }
    ],
    "rejectedSources": [
      {
        "platform": "fanatics",
        "priceCents": 1332500,
        "reason": "MAD outlier (z=6.04)",
        "zScore": 6.036348101265823
      },
      {
        "platform": "beezie",
        "priceCents": 307731,
        "reason": "listing off-anchor (0.58x of $5350 — likely wrong grade/variant)"
      },
      {
        "platform": "collector-crypt",
        "priceCents": 274210,
        "reason": "listing off-anchor (0.51x of $5350 — likely wrong grade/variant)"
      }
    ],
    "flags": [
      "insufficient_sources",
      "consensus_above_lowest_ask"
    ],
    "sourceCount": 2,
    "roundId": "neo1-1st-18_1781041924799",
    "timestamp": "2026-06-09T21:52:04.799Z",
    "rawSourceCount": 3,
    "sourceFamilies": [
      "ebay-sold",
      "psa-apr"
    ],
    "askCount": 4,
    "lowestAskCents": 351046
  },
  "jp-vs-091": {
    "cardId": "jp-vs-091",
    "consensusPriceCents": 1588230,
    "confidenceLower": 1588230,
    "confidenceUpper": 1588230,
    "contributingSources": [
      {
        "platform": "pricecharting",
        "family": "ebay-sold",
        "kind": "realized",
        "priceCents": 1588230,
        "confidence": 0.9,
        "reliability": 0.8759695416488645,
        "weight": 1.7181859553979566,
        "source": "pc_sold",
        "compCount": 5
      },
      {
        "platform": "ebay",
        "family": "ebay-sold",
        "kind": "ask",
        "priceCents": 1850000,
        "confidence": 0.6,
        "reliability": 0.7742201425692438,
        "weight": 0,
        "source": "ebay_active",
        "compCount": 5
      },
      {
        "platform": "courtyard",
        "family": "courtyard",
        "kind": "ask",
        "priceCents": 1242596,
        "confidence": 0.95,
        "reliability": 0.8069461917475208,
        "weight": 0,
        "source": "courtyard_seeded",
        "compCount": 11
      },
      {
        "platform": "tcgplayer",
        "family": "tcgplayer",
        "kind": "ask",
        "priceCents": 1180221,
        "confidence": 0.95,
        "reliability": 0.7179784600256658,
        "weight": 0,
        "source": "tcgplayer_seeded",
        "compCount": 12
      },
      {
        "platform": "cardmarket",
        "family": "cardmarket",
        "kind": "ask",
        "priceCents": 2047500,
        "confidence": 0.2,
        "reliability": 0.6300420280640746,
        "weight": 0,
        "source": "cardmarket_active",
        "compCount": 1
      },
      {
        "platform": "beezie",
        "family": "beezie",
        "kind": "ask",
        "priceCents": 1176208,
        "confidence": 0.95,
        "reliability": 0.4352634131468657,
        "weight": 0,
        "source": "beezie_seeded",
        "compCount": 8
      },
      {
        "platform": "collector-crypt",
        "family": "collector-crypt",
        "kind": "ask",
        "priceCents": 1256174,
        "confidence": 0.95,
        "reliability": 0.5608177823190338,
        "weight": 0,
        "source": "collector-crypt_seeded",
        "compCount": 10
      }
    ],
    "rejectedSources": [
      {
        "platform": "goldin",
        "priceCents": 68265000,
        "reason": "MAD outlier (z=39.78)",
        "zScore": 39.77764510645187
      },
      {
        "platform": "fanatics",
        "priceCents": 2700000,
        "reason": "implausible vs anchor (1.70x of $15882, thin source)"
      },
      {
        "platform": "alt",
        "priceCents": 147000,
        "reason": "listing off-anchor (0.09x of $15882 — likely wrong grade/variant)"
      }
    ],
    "flags": [
      "insufficient_sources",
      "consensus_above_lowest_ask"
    ],
    "sourceCount": 1,
    "roundId": "jp-vs-091_1781041924800",
    "timestamp": "2026-06-09T21:52:04.800Z",
    "rawSourceCount": 1,
    "sourceFamilies": [
      "ebay-sold"
    ],
    "askCount": 6,
    "lowestAskCents": 1176208
  },
  "base5-1st-83": {
    "cardId": "base5-1st-83",
    "consensusPriceCents": 798656,
    "confidenceLower": 793000,
    "confidenceUpper": 798656,
    "contributingSources": [
      {
        "platform": "goldin",
        "family": "goldin",
        "kind": "realized",
        "priceCents": 793000,
        "confidence": 0.8,
        "reliability": 0.3873318510042184,
        "weight": 0.3098373743894235,
        "source": "goldin-auctions",
        "compCount": 1
      },
      {
        "platform": "pricecharting",
        "family": "ebay-sold",
        "kind": "realized",
        "priceCents": 798656,
        "confidence": 0.9,
        "reliability": 0.8776557273595241,
        "weight": 0.8607467183689075,
        "source": "pc_sold",
        "compCount": 5
      },
      {
        "platform": "fanatics",
        "family": "fanatics-pwcc",
        "kind": "realized",
        "priceCents": 470000,
        "confidence": 0.7,
        "reliability": 0.22584955814150254,
        "weight": 0.15807986478902022,
        "source": "fanatics-pwcc",
        "compCount": 1
      },
      {
        "platform": "point130",
        "family": "ebay-sold",
        "kind": "realized",
        "priceCents": 589000,
        "confidence": 0.72,
        "reliability": 0.00243,
        "weight": 0.0015151165967343557,
        "source": "point130-sold",
        "compCount": 3
      },
      {
        "platform": "ebay",
        "family": "ebay-sold",
        "kind": "ask",
        "priceCents": 1499995,
        "confidence": 0.125,
        "reliability": 0.7697660427707731,
        "weight": 0,
        "source": "ebay_active",
        "compCount": 1
      },
      {
        "platform": "courtyard",
        "family": "courtyard",
        "kind": "ask",
        "priceCents": 532468,
        "confidence": 0.95,
        "reliability": 0.7911034653673934,
        "weight": 0,
        "source": "courtyard_seeded",
        "compCount": 10
      },
      {
        "platform": "tcgplayer",
        "family": "tcgplayer",
        "kind": "ask",
        "priceCents": 527955,
        "confidence": 0.95,
        "reliability": 0.7023500597468302,
        "weight": 0,
        "source": "tcgplayer_seeded",
        "compCount": 10
      },
      {
        "platform": "alt",
        "family": "alt",
        "kind": "ask",
        "priceCents": 760560,
        "confidence": 0.6666666666666666,
        "reliability": 0.3414033186938107,
        "weight": 0,
        "source": "alt_sold",
        "compCount": 2
      },
      {
        "platform": "beezie",
        "family": "beezie",
        "kind": "ask",
        "priceCents": 655139,
        "confidence": 0.95,
        "reliability": 0.42023419635785275,
        "weight": 0,
        "source": "beezie_seeded",
        "compCount": 11
      }
    ],
    "rejectedSources": [
      {
        "platform": "psa-apr",
        "priceCents": 397000,
        "reason": "implausible vs anchor (0.50x of $7987)"
      }
    ],
    "flags": [
      "consensus_above_lowest_ask"
    ],
    "sourceCount": 3,
    "roundId": "base5-1st-83_1781041924800",
    "timestamp": "2026-06-09T21:52:04.800Z",
    "rawSourceCount": 4,
    "sourceFamilies": [
      "goldin",
      "ebay-sold",
      "fanatics-pwcc"
    ],
    "askCount": 5,
    "lowestAskCents": 527955
  },
  "base2-1st-3": {
    "cardId": "base2-1st-3",
    "consensusPriceCents": 730000,
    "confidenceLower": 730000,
    "confidenceUpper": 730000,
    "contributingSources": [
      {
        "platform": "pricecharting",
        "family": "ebay-sold",
        "kind": "realized",
        "priceCents": 730000,
        "confidence": 0.8500000000000001,
        "reliability": 0.8792967182078573,
        "weight": 1.4569278755999446,
        "source": "pc_sold",
        "compCount": 4
      },
      {
        "platform": "ebay",
        "family": "ebay-sold",
        "kind": "ask",
        "priceCents": 795000,
        "confidence": 0.6,
        "reliability": 0.7636731756630902,
        "weight": 0,
        "source": "ebay_active",
        "compCount": 6
      },
      {
        "platform": "alt",
        "family": "alt",
        "kind": "ask",
        "priceCents": 875000,
        "confidence": 0.4,
        "reliability": 0.3466070421197711,
        "weight": 0,
        "source": "alt-ask",
        "compCount": 1
      }
    ],
    "rejectedSources": [
      {
        "platform": "goldin",
        "priceCents": 42500,
        "reason": "implausible vs anchor (0.06x of $7300, thin source)"
      },
      {
        "platform": "fanatics",
        "priceCents": 338000,
        "reason": "implausible vs anchor (0.46x of $7300, thin source)"
      },
      {
        "platform": "psa-apr",
        "priceCents": 300100,
        "reason": "implausible vs anchor (0.41x of $7300)"
      },
      {
        "platform": "courtyard",
        "priceCents": 212888,
        "reason": "listing off-anchor (0.29x of $7300 — likely wrong grade/variant)"
      },
      {
        "platform": "tcgplayer",
        "priceCents": 208860,
        "reason": "listing off-anchor (0.29x of $7300 — likely wrong grade/variant)"
      },
      {
        "platform": "beezie",
        "priceCents": 237967,
        "reason": "listing off-anchor (0.33x of $7300 — likely wrong grade/variant)"
      },
      {
        "platform": "collector-crypt",
        "priceCents": 232370,
        "reason": "listing off-anchor (0.32x of $7300 — likely wrong grade/variant)"
      }
    ],
    "flags": [
      "insufficient_sources"
    ],
    "sourceCount": 1,
    "roundId": "base2-1st-3_1781041924800",
    "timestamp": "2026-06-09T21:52:04.800Z",
    "rawSourceCount": 1,
    "sourceFamilies": [
      "ebay-sold"
    ],
    "askCount": 2,
    "lowestAskCents": 795000
  }
}